django_label_tag_attr-1.0.2.dist-info/DESCRIPTION.rst
django_label_tag_attr-1.0.2.dist-info/METADATA
django_label_tag_attr-1.0.2.dist-info/metadata.json
django_label_tag_attr-1.0.2.dist-info/RECORD
django_label_tag_attr-1.0.2.dist-info/top_level.txt
django_label_tag_attr-1.0.2.dist-info/WHEEL
label_tag_attr/__init__.py
label_tag_attr/models.py
