Metadata-Version: 2.0
Name: django-label-tag-attr
Version: 1.0.2
Summary: Add css classes and html tag attributes to django form's label.
Home-page: https://github.com/c-bata/django-label-tag-attr
Author: Masashi Shibata <contact@c-bata.link>
Author-email: contact@c-bata.link
License: MIT License
Keywords: django,form,label,label_tag_attr
Platform: UNKNOWN
Requires-Dist: Django
